polars_grouper-0.3.0.dist-info/METADATA
polars_grouper-0.3.0.dist-info/WHEEL
polars_grouper/__init__.py
polars_grouper/_internal.pyi
polars_grouper/typing.py
polars_grouper/_internal.abi3.so
polars_grouper-0.3.0.dist-info/RECORD
